[{"url": "http://www.iwupi.com/2008/09/01/august-best-design/", "title": "8\u6708\u5341\u5927\u6700\u5177\u521b\u610f\u548c\u8da3\u5473\u7684\u8bbe\u8ba1", "tags": "\u521b\u610f \u5341\u5927 \u8bbe\u8ba1 ", "name": "laotu", "posttime": "2008-09-01 23:30:17", "ip": "116.232.254.29", "mark": 2, "note": "\u516b\u6708\u8fc7\u53bb\u4e86\uff0c[\u7231\u7269\u7656]\u9009\u51fa\u4e86\u6574\u4e2a\u6708\u6700\u5177\u521b\u65b0\u610f\u8bc6\uff0c\u6700\u65b0\u5947\u7279\u7684\u8bbe\u8ba1\u548c\u4ea7\u54c1\uff0c\u4e00\u5171\u662f10\u4e2a\uff0c\u5176\u4e2d\u6709\u771f\u7684windows\u89c6\u7a97\uff0c\u80fd\u591f\u5728\u7a7a\u6c14\u4e2d\u5199\u5b57\u7684\u7b14\uff0c\u6c34\u505a\u7684\u684c\u5b50\u7b49\u3002\u4e0b\u9762\u662f10\u5927\u8bbe\u8ba1\u4ea7\u54c1\u7684\u5168\u90e8\u5185\u5bb9\uff0c\u6211\u4eec\u4f1a\u5217\u51fa\u8bc4\u9009\u7684\u7406\u7531\u3002", "imagename": "9065064bcbe94df69251b39976d65469.jpg", "infoid": 88603, "category": "technology_design", "isanchordig": 1, "ischecked": 0, "isdelete": 0, "categoryclass": "technology", "via": null, "real_tags": ["\u521b\u610f", "\u5341\u5927", "\u8bbe\u8ba1"]}, {"url": "http://jiaogen.com/index.php/archives/2367", "title": "\u96c5\u864e\u90ae\u4ef6\u5ba2\u6237\u7aef\u53d1\u5e03", "tags": "yahoo ", "name": "moyuhappy", "posttime": "2008-09-01 23:06:09", "ip": "125.77.239.47", "mark": 2, "note": "\u611f\u8c22\u60a8\u957f\u671f\u4f7f\u7528\u96c5\u864e\u90ae\u7bb1\u53ca\u76f8\u5173\u4ea7\u54c1\uff0c\u5e76\u4e00\u5982\u65e2\u5f80\u7684\u5927\u529b\u652f\u6301\u96c5\u864e\u90ae\u7bb1\u7684\u53d1\u5c55\u3002\u5728\u96c5\u864e\u90ae\u7bb1\u4f17\u591a\u7528\u6237\u4e2d\uff0c\u6211\u4eec\u7279\u522b\u9080\u8bf7\u4e00\u90e8\u5206\u70ed\u5fc3\u7528\u6237\u516c\u6d4b\u96c5\u864e\u90ae\u4ef6\u5ba2\u6237\u7aef\u8f6f\u4ef6\u3002", "imagename": "", "infoid": 88598, "category": "technology_google", "isanchordig": 1, "ischecked": 0, "isdelete": 0, "categoryclass": "technology", "via": null, "real_tags": ["yahoo"]}, {"url": "http://www.webspot.net.cn/?p=206", "title": "LogoGenerador-\u5728\u7ebf\u5236\u4f5clogo", "tags": "logo logo\u5236\u4f5c ", "name": "yava555", "posttime": "2008-09-01 21:27:55", "ip": "221.0.107.218", "mark": 2, "note": "LogoGenerador[www.logogenerador.com] \u662f\u4e00\u4e2a\u5728\u7ebf\u5236\u4f5clogo\u7684\u7ad9\u70b9\uff0c\u64cd\u4f5c\u975e\u5e38\u7b80\u5355\uff0c\u5236\u4f5c\u51fa\u6765\u7684logo\u4e5f\u5f88\u6f02\u4eae\u3002", "imagename": "c46048b85c9d44ac9104de29dbe93f8b.jpg", "infoid": 88586, "category": "technology_design", "isanchordig": 1, "ischecked": 0, "isdelete": 0, "categoryclass": "technology", "via": null, "real_tags": ["logo", "logo\u5236\u4f5c"]}, {"url": "http://www.digiex.cn/expodoc/200891/080901202551961.html", "title": "8\u4e2a\u589e\u5f3aWindows\u6548\u7387\u7684\u5fc5\u5907\u8f6f\u4ef6(\u514d\u8d39)", "tags": "windows \u8f6f\u4ef6 \u514d\u8d39 ", "name": "shfengyi", "posttime": "2008-09-01 20:33:01", "ip": "58.24.242.103", "mark": 2, "note": "\u4eca\u5929\u6574\u7406\u4e86\u4e00\u4e0bXP\u4e0b\u7684\u8f6f\u4ef6\uff0c\u539f\u6765\u6211\u5b89\u88c5\u4e86\u51e0\u5341\u516c\u65a4\u7684\u8f6f\u4ef6\uff0c250G\u7684\u786c\u76d8\u51e0\u4e4e\u7528\u5b8c\uff0c\u6240\u4ee5\u5378\u8f7d\u4e86\u5f88\u591a\u5f88\u5c11\u7528\u7684\u8f6f\u4ef6\u3002\u5728\u5378\u8f7d\u8fc7\u7a0b\u4e2d\uff0c\u6211\u53d1\u73b0\u6709\u4e0d\u5c11\u8f6f\u4ef6\u662f\u5341\u5206\u503c\u5f97\u63a8\u8350\u7684\uff0c\u8fd9\u4e9b\u8f6f\u4ef6\u80fd\u5927\u5927\u63d0\u9ad8windows\u6548\u7387\uff0c\u800c\u4e14\u90fd\u662f\u514d\u8d39\u7684\u3002", "imagename": "bd3c0631e82846699a9c66a2c793d691.jpg", "infoid": 88577, "category": "technology_software", "isanchordig": 1, "ischecked": 0, "isdelete": 0, "categoryclass": "technology", "via": null, "real_tags": ["windows", "\u8f6f\u4ef6", "\u514d\u8d39"]}, {"url": "http://mobile.kugou.com/", "title": "\u624b\u673a\u7248\u9177\u72d7(KuGou Mobile)\u6b63\u5f0f\u53d1\u5e03", "tags": "\u9177\u72d7 KuGou \u624b\u673a\u9177\u72d7 ", "name": "spmobile", "posttime": "2008-09-01 20:14:47", "ip": "222.95.130.104", "mark": 5, "note": "\u8fd1\u65e5\uff0c\u9177\u72d7\u516c\u53f8\u6b63\u5f0f\u5bf9\u5916\u53d1\u5e03\u4e86\u9177\u72d7\u97f3\u4e50\u7684\u624b\u673a\u7248\u64ad\u653e\u8f6f\u4ef6\u2014\u2014\u624b\u673a\u9177\u72d7\uff08\u82f1\u6587\u540d\u4e3a\u201cKuGou Mobile\u201d\uff09\u3002\u636e\u6089\uff0c\u624b\u673a\u9177\u72d7\u662f\u9177\u72d7\u516c\u53f8\u72ec\u7acb\u5f00\u53d1\u7684\u4e00\u6b3e\u7528\u4e8e\u624b\u673a\u7ec8\u7aef\u7684\u97f3\u4e50\u64ad\u653e\u8f6f\u4ef6\uff0c\u62e5\u6709\u81ea\u4e3b\u7814\u53d1\u7684\u72ec\u7acb\u97f3\u9891\u7f16\u7801\u5668\uff1b\u652f\u6301\u64ad\u653e\u6240\u6709\u7684\u97f3\u9891\u6587\u4ef6\uff1b\u652f\u6301\u9177\u72d7\u72ec\u521b\u7684KRC\u52a8\u611f\u6b4c\u8bcd\u6280\u672f\uff08\u80fd\u591f\u5b9e\u73b0\u9010\u5b57\u64ad\u653e\uff0c\u517c\u5bb9\u4f20\u7edf\u7684LRC\u6b4c\u8bcd\uff09\uff1b\u5177\u5907\u81ea\u52a8\u4e0b\u8f7d\u6b4c\u8bcd\u529f\u80fd\uff08\u987b\u7528\u6237\u5f00\u901aGPRS\u6216\u8005WIFI\u7b49\u7f51\u7edc\u8fde\u63a5\uff09\uff1b\u540c\u65f6\u517c\u5177\u6709\u64cd\u4f5c\u7b80\u5355\u3001\u5b8c\u5168\u514d\u8d39\u3001\u4f4e\u8d44\u6e90\u5360\u7528\u7b49\u7279\u70b9\u3002", "imagename": "835e0600d6ed4a0c94bb9e45cc1125b9.jpg", "infoid": 88573, "category": "technology_software", "isanchordig": 1, "ischecked": 0, "isdelete": 0, "categoryclass": "technology", "via": null, "real_tags": ["\u9177\u72d7", "kugou", "\u624b\u673a\u9177\u72d7"]}, {"url": "http://www.itvisitor.com/archives/274.html", "title": "\u65e7\u4e66\u4ea4\u6362\u670d\u52a1:bookmooch", "tags": "\u4e66 web2.0 ", "name": "wendong", "posttime": "2008-09-01 18:34:37", "ip": "123.235.45.156", "mark": 6, "note": "bookmooch\u662f\u5728\u4e00\u4e2a\u5728\u7ebf\u65e7\u4e66\u4ea4\u6362\u7f51\u7ad9\uff0c\u7f51\u7ad9\u56fd\u9645\u5316\u7a0b\u5ea6\u8f83\u9ad8\uff0c\u63d0\u4f9b\u4e86\u591a\u79cd\u8bed\u8a00\u670d\u52a1\uff0c\u6ce8\u518c\u540e\uff0c\u4f60\u53ef\u4ee5\u5c06\u4f60\u624b\u4e2d\u7684\u65e7\u4e66\u6302\u724c\uff0c\u4e00\u65e6\u6709\u4eba\u627e\u5230\u5e76\u9700\u8981\u8fd9\u672c\u4e66\u7684\u65f6\u5019\uff0c\u4f60\u5c31\u53ef\u4ee5\u628a\u6570\u90ae\u5bc4\u7ed9\u4ed6\uff0c\u6ce8\u610f\u90ae\u8d39\u662f\u9700\u8981\u4f60\u4ed8\u7684\uff0c\u8fd9\u4e2a\u65f6\u5019\u4f60\u5c31\u5f97\u5230\u4e00\u4e2a\u70b9...", "imagename": "", "infoid": 88564, "category": "technology_web2", "isanchordig": 1, "ischecked": 0, "isdelete": 0, "categoryclass": "technology", "via": null, "real_tags": ["web2.0"]}, {"url": "http://www.digiex.cn/expodoc/200891/080901163722632.html", "title": "10\u5927\u535a\u5ba2\u8f6f\u4ef6\u70b9\u8bc4", "tags": "\u535a\u5ba2 \u8f6f\u4ef6 \u5efa\u7ad9 ", "name": "shfengyi", "posttime": "2008-09-01 16:47:37", "ip": "58.24.242.103", "mark": 2, "note": "\u9009\u4e00\u5957\u535a\u5ba2\u8f6f\u4ef6\u5f80\u5f80\u8981\u77bb\u524d\u987e\u540e\uff0c\u552f\u6050\u9009\u9519\u8f6f\u4ef6\u7ad9\u9519\u961f\uff0c\u7279\u522b\u662f\u5bf9\u4e8e\u535a\u5ba2\u65b0\u624b\u6765\u8bf4\u3002\u53ef\u4f9b\u9009\u62e9\u7684\u535a\u5ba2\u8f6f\u4ef6\u548c\u5185\u5bb9\u7ba1\u7406\u8f6f\u4ef6\u592a\u591a\u592a\u591a\u4e86\u3002\u4ece\u6210\u5343\u4e0a\u4e07\u7684\u7684\u8f6f\u4ef6\u4e2d\u62e9\u5584\u800c\u4ece\u53ef\u4e0d\u662f\u4e00\u4ef6\u5bb9\u6613\u7684\u4e8b\u3002\u4e0b\u9762\u6211\u4eec\u6765\u770b\u770b\u8fd910\u4e2a\u6700\u53d7\u6b22\u8fce\u7684\u535a\u5ba2\u8f6f\u4ef6\u3002", "imagename": "3336d0830e1d41a4acf05ba2772b8636.jpg", "infoid": 88554, "category": "technology_software", "isanchordig": 1, "ischecked": 0, "isdelete": 0, "categoryclass": "technology", "via": null, "real_tags": ["\u535a\u5ba2", "\u8f6f\u4ef6", "\u5efa\u7ad9"]}, {"url": "http://www.comsharp.com/GetKnowledge/zh-CN/TeamBlogTimothyPage_K492.aspx", "title": "\u5fae\u8f6f\u516c\u5e03\u5b8c\u6574\u641c\u7d22\u6218\u7565", "tags": "\u5fae\u8f6f ", "name": "comsharp", "posttime": "2008-09-01 16:09:44", "ip": "122.4.117.206", "mark": 4, "note": "\u5fae\u8f6f\u8ba1\u5212\u4ee54\u4ebf8600\u4e07\u7f8e\u5706\u6536\u8d2d\u6b27\u6d32\u7684\u4ef7\u683c\u5bf9\u6bd4\u4e0e\u8d2d\u7269\u7f51\u7ad9 Ciao\uff0c\u4ee5\u589e\u5f3a\u5176 Live Search \u8868\u73b0\u3002\u5fae\u8f6f\u6b27\u6d32\u5728\u7ebf\u6d88\u8d39\u4e1a\u52a1\u526f\u603b\u88c1 John Mangelaars \u79f0\uff0c\u5c06 Ciao \u96c6\u6210\u5230 Live Search \u662f\u5176\u6b27\u6d32\u5546\u4e1a\u641c\u7d22\u6a21\u5f0f\u7684\u5f00\u7aef\u3002", "imagename": "dd3272bebf03472a8e4c8f2c5574ceab.jpg", "infoid": 88549, "category": "technology_web2", "isanchordig": 1, "ischecked": 0, "isdelete": 0, "categoryclass": "technology", "via": null, "real_tags": ["\u5fae\u8f6f"]}, {"url": "http://www.comsharp.com/GetKnowledge/zh-CN/It_News_K491.aspx", "title": "SharePoint \u5728\u4f01\u4e1a\u95e8\u6237\u5e02\u573a\u8179\u80cc\u53d7\u654c", "tags": "", "name": "comsharp", "posttime": "2008-09-01 15:15:28", "ip": "122.4.117.206", "mark": 4, "note": "\u636e\u8457\u540d\u5185\u5bb9\u7ba1\u7406\u7cfb\u7edf(CMS) \u5206\u6790\u5546 CMS Watch \u62a5\u5bfc\uff0c\u5fae\u8f6f\u5728\u4f01\u4e1a\u95e8\u6237\u7cfb\u7edf SharePoint \u4e0a\u7684\u6210\u529f\uff0c\u5f15\u53d1 IBM, SAP, Oracle \u4e00\u7c7b\u7684\u9ad8\u7aef\u5382\u5546\u7eb7\u7eb7\u52a0\u529b\uff0c\u5728\u4f01\u4e1a\u96c6\u6210\u4e0e Web 2.0 \u529f\u80fd\u4e0a\u52a0\u5927\u5de5\u592b\u4ee5\u593a\u56de\u4ed6\u4eec\u7684\u5e02\u573a\u3002", "imagename": "06d1c32f2c2e4b269a455e851045d1c9.jpg", "infoid": 88538, "category": "technology_web2", "isanchordig": 1, "ischecked": 0, "isdelete": 0, "categoryclass": "technology", "via": null, "real_tags": null}, {"url": "http://my.dongua.com/wewa/blog!entry/2414.entry", "title": "11\u4e2a\u5e05\u5230\u6389\u6e23\u7684DIY NDS", "tags": "NDS DIY ", "name": "sasawe", "posttime": "2008-09-01 14:39:11", "ip": "219.136.12.192", "mark": 2, "note": "\u5f53\u4f60\u57cb\u6028NDS\uff08NDSL\uff09\u4ec5\u6709\u90a3\u51e0\u6b3e\u989c\u8272\uff0c\u5f53\u4f60\u57cb\u6028NDS\uff08NDSL\uff09\u7684\u9650\u91cf\u7248\u5f88\u4e11\uff0c\u5f53\u4f60\u57cb\u6028\u81ea\u5df1\u7684NDS\uff08NDSL\uff09\u4e0d\u591f\u4e2a\u6027\u5316\uff0c\u73b0\u5728\u4e0d\u5982\u53c2\u8003\u4e00\u4e0b\u6211\u4eec\u4e3a\u60a8\u4ecb\u7ecd\u768411\u4e2a\u5e05\u5f97\u6389\u6e23\u7684DIY NDS\u5427\uff0c\u5e0c\u671b\u60a8\u53ef\u4ee5\u4ece\u4e2d\u5f97\u5230\u542f\u53d1~\u60f3\u8981\u4ee4\u60a8\u7684NDS\uff08NDSL\uff09\u8f6f\u786c\u517c\u4fee\uff0c\u52a8\u624b\u5427\uff01", "imagename": "aa263e990a8b47fca426f1e458ba858b.jpg", "infoid": 88530, "category": "technology_games", "isanchordig": 1, "ischecked": 0, "isdelete": 0, "categoryclass": "technology", "via": null, "real_tags": ["nds", "diy"]}, {"url": "http://www.mrsakura.com/logs/27584014.html", "title": "\u53ef\u4ee5\u5f53\u4f5c\u5ea7\u6905\u7684\u952e\u76d8\u94ae", "tags": "\u521b\u610f \u5bb6\u5c45 ", "name": "mrsakura", "posttime": "2008-09-01 14:35:09", "ip": "123.113.203.97", "mark": 2, "note": "\u6574\u5929\u9762\u5bf9\u7740\u952e\u76d8\u4e0a\u7684\u5c0f\u5c0f\u6309\u94ae\uff0c\u6bcf\u5929\u90fd\u5728\u90a3\u51e0\u5341\u4e2a\u5b57\u6bcd\u4e0a\u6572\u6765\u6253\u53bb\uff0c\u6709\u6ca1\u6709\u60f3\u8fc7\u628a\u8fd9\u4e9b\u539f\u672c\u751f\u786c\u7684\u4e1c\u897f\u53d8\u5f97\u751f\u6d3b\u5316\u4e00\u4e9b\u5462\uff0c\u8ba9\u5b83\u4eec\u6210\u4e3a\u4f60\u751f\u6d3b\u4e2d\u7684\u4e00\u79cd\u5bb6\u5c45\u4e50\u8da3\u3002\u4eca\u5929QQ\u5c31\u7ed9\u5927\u5bb6\u5e26\u6765\u7684\u8fd9\u4e9b\u5bb6\u5c45\u5c31\u662f\u7528\u952e\u76d8\u6309\u94ae\u505a\u6210\u7684\u5ea7\u6905", "imagename": "efe3339e74694bc0bbe247ee78c6aa20.jpg", "infoid": 88529, "category": "technology_design", "isanchordig": 1, "ischecked": 0, "isdelete": 0, "categoryclass": "technology", "via": null, "real_tags": ["\u521b\u610f", "\u5bb6\u5c45"]}, {"url": "http://www.mrsakura.com/logs/27693058.html", "title": "\u7231\u62a4\u624b\u8155 \u53ef\u7231\u7684\u9f20\u6807\u4f34\u4fa3", "tags": "\u9f20\u6807 ", "name": "mrsakura", "posttime": "2008-09-01 14:34:35", "ip": "123.113.203.97", "mark": 2, "note": "\u540cSaKuRa\u548cQQ\u4e00\u6837\u7684\u7f51\u7edc\u4eba\u58eb\uff0c\u6bcf\u5929\u90fd\u662f\u9f20\u6807\u952e\u76d8\u4e0d\u79bb\u624b\uff0c\u81ea\u5df1\u5f88\u591a\u670b\u53cb\u4e5f\u90fd\u5f97\u4e86\u952e\u76d8\u624b\u6216\u8005\u9f20\u6807\u624b\uff01\u54ce\uff0c\u5de5\u4f5c\u4e4b\u4e2d\u8fd8\u662f\u8981\u65f6\u5e38\u7684\u953b\u70bc\u4e00\u4e0b\u81ea\u5df1\u8eab\u4f53\u7684\u67d0\u51e0\u4e2a\u73af\u8282", "imagename": "5d4c07b502ed43e8b410bf36fb10c7c9.jpg", "infoid": 88528, "category": "technology_gadgets", "isanchordig": 1, "ischecked": 0, "isdelete": 0, "categoryclass": "technology", "via": null, "real_tags": ["\u9f20\u6807"]}, {"url": "http://www.freedomblog.cn/antivirus/pc-tools-antivirus-for-free.html", "title": "\u514d\u8d39\u7248PC Tools\u6740\u6bd2\u8f6f\u4ef6", "tags": "PC Tools \u514d\u8d39 \u6740\u6bd2\u8f6f\u4ef6 ", "name": "knight34", "posttime": "2008-09-01 12:42:05", "ip": "202.101.116.150", "mark": 2, "note": "PC Tools AntiVirus \u9488\u5bf9\u6076\u610f\u75c5\u6bd2\u611f\u67d3\uff0c\u514d\u8d39\u63d0\u4f9b\u5f3a\u5927\u4fdd\u62a4\u3002\u62e5\u6709PC Tools AntiVirus \u514d\u8d39\u7248\u672c\uff0c\u60a8\u5c06\u53d7\u5230\u4fdd\u62a4\uff0c\u9632\u6b62\u6700\u6076\u6bd2\u7684\u7f51\u7edc\u4f20\u64ad\u5a01\u80c1\u75c5\u6bd2\u8fdb\u5165\u60a8\u7684\u7535\u8111\uff0c\u83b7\u53d6\u60a8\u7684\u4e2a\u4eba\u4fe1\u606f\u3002\u4e0a\u7f51\u65f6\uff0c\u9762\u5bf9\u5feb\u901f\u4f20\u64ad\u7684\u6700\u65b0\u75c5\u6bd2\u548c\u8815\u866b\uff0c\u5982\uff1aNetsky\u3001 Mytob\u548cMyDoom\uff0c\u82e5\u6ca1\u6709\u4fdd\u62a4\u63aa\u65bd\uff0c\u4f1a\u5728\u6570\u5206\u949f\u4e4b\u5185\u5c31\u88ab\u611f\u67d3\u3002\r\n\r\n\u3000\u3000\u4e00\u65e6\u611f\u67d3\uff0c\u901a\u5e38\uff0c\u75c5\u6bd2\u5c06\u8bd5\u56fe\u901a\u8fc7\u60a8\u7684\u7535\u90ae\u8054\u7cfb\u4eba\u548c\u8054\u7f51\u7535\u8111\uff0c\u5c06\u81ea\u8eab\u4f20\u64ad\u81f3\u60a8\u7684\u670b\u53cb\u3001\u4eb2\u4eba\u53ca\u5176\u4ed6\u76f8\u5173\u4eba\u5458\u3002\u9ed1\u5ba2\u8fd8\u4f1a\u5229\u7528\u75c5\u6bd2\u5165\u4fb5\u60a8\u7684\u7535\u8111\uff0c\u7528\u5b83\u5bf9\u5176\u4ed6\u7535\u8111\u53d1\u8d77\u653b\u51fb\u6216\u53d1\u9001\u5927\u91cf\u5783\u573e\u90ae\u4ef6\u3002\r\n\r\n\u3000\u3000\u8fd9\u5c31\u662fPC Tools AntiVirus \u514d\u8d39\u7248\u672c\u8981\u4e3a\u60a8\u63d0\u4f9b\u4e16\u754c\u9886\u5148\u7684\u9632\u62a4\u7684\u539f\u56e0\u3002\u51ed\u501f\u5176\u5feb\u901f\u7684\u6570\u636e\u5e93\u66f4\u65b0\u3001IntelliGuard\u2122 \u5b9e\u65f6\u4fdd\u62a4\u53ca\u5168\u9762\u7684\u7cfb\u7edf\u626b\u63cf\uff0c\u786e\u4fdd\u60a8\u7684\u7cfb\u7edf\u6ca1\u6709\u75c5\u6bd2\u3001\u59cb\u7ec8\u5b89\u5168\u3002PC Tools\u7684\u4ea7\u54c1\u6bcf\u5929\u88ab\u6570\u767e\u4e07\u7684\u7528\u6237\u4f7f\u7528\uff0c\u7528\u4ee5\u4fdd\u62a4\u5176\u5bb6\u7528\u548c\u5546\u7528\u8ba1\u7b97\u673a\u514d\u906d\u7f51\u7edc\u5a01\u80c1\uff0c\u6df1\u53d7\u7528\u6237\u4fe1\u4efb\u3002", "imagename": "8d7ed073f8c443f7b8378e29756f56d3.gif", "infoid": 88505, "category": "technology_software", "isanchordig": 1, "ischecked": 0, "isdelete": 0, "categoryclass": "technology", "via": null, "real_tags": ["pc", "tools", "\u514d\u8d39", "\u6740\u6bd2\u8f6f\u4ef6"]}, {"url": null, "title": "Adobe\u5c06\u63a8\u57fa\u4e8ePPC\u5e73\u53f0\u7684Photoshop\u8f6f\u4ef6", "tags": "Adobe PPC Photoshop \u8f6f\u4ef6 ", "name": "yinyin", "posttime": "2008-09-01 10:57:27", "ip": "117.88.34.32", "mark": 4, "note": "&nbsp;&nbsp;&nbsp;&nbsp;&nbsp;&nbsp;&nbsp; \u8457\u540d\u7684\u56fe\u65b0\u5904\u7406\u8f6f\u4ef6\u4f9b\u5e94\u5546\uff0cPhotoshop\u7684\u4e1c\u5bb6Adobe\u516c\u53f8\u5c06\u63a8\u51faWindows Mobile\u53ef\u7528\u7684Photoshop\u3002\u968f\u7740\u96c5\u864e\u3001Google\u7b49\u4e92\u8054\u7f51\u5185\u5bb9\u548c\u641c\u7d22\u670d\u52a1\u5546\u5c06\u670d\u52a1\u5ef6\u4f38\u5230\u624b\u673a\u9886\u57df\uff0c\u6ca1\u60f3\u5230Adobe\u516c\u53f8\u8d70\u5728\u4e86\u56fe\u50cf\u5904\u7406\u7684\u524d\u5217\u3002\r\n<P>\u3000\u3000\u4f17\u6240\u5468\u77e5\uff0cAdobe\u516c\u53f8\u63a8\u51fa\u7684\u8457\u540d\u56fe\u50cf\u5904\u7406\u8f6f\u4ef6Photoshop\u5728\u5168\u4e16\u754c\u62e5\u6709\u5927\u91cf\u7684\u4f7f\u7528\u8005\uff0c\u76f8\u4fe1\u8fd9\u4e9b\u7528\u6237\u5728WindowS Mobile\u667a\u80fd\u624b\u673a\u4e0a\u7528\u5230Photoshop\u4e00\u5b9a\u975e\u5e38\u60ca\u5947\u3002</P>\r\n<P><IMG src=\"http://mobile.comm.ccidnet.com/col/attachment/2008/8/1614461.jpg\"></P>\r\n<P>&nbsp;&nbsp;&nbsp;&nbsp;&nbsp;&nbsp;&nbsp; \u636e\u6089\uff0c\u79fb\u52a8\u7248Photoshop\u5f00\u53d1\u8ba1\u5212\u5c06\u4e8e10\u6708\u53d1\u5e03\uff0c\u4e0b\u4e2a\u6708\u673a\u4f1a\u6709\u6d4b\u8bd5\u7248\u4ea7\u54c1\u63a8\u51fa\u3002\u9996\u6279\u652f\u6301\u7684\u624b\u673a\u5305\u62ecMotorola Q 9h,Q Music 9m, Samsung Blackjack I,II,Palm Treo 750w\u7b49\u3002\u79fb\u52a8\u7248Photoshop\u5c06\u652f\u6301\u5e38\u7528\u7684\u7f16\u8f91\u64cd\u4f5c\uff0c\u5982\u65cb\u8f6c\u3001\u526a\u5207\u3001\u81ea\u52a8\u4fee\u6b63\u7b49\uff0c\u8be5\u8f6f\u4ef6\u5c06\u968fPhotoshop.com\u51fa\u552e\u7684\u7a7a\u95f4\u4e00\u540c\u63d0\u4f9b\u3002</P>\r\n<P>\u6765\u6e90\uff1a\u624b\u673a\u4e2d\u56fd</P>", "imagename": null, "infoid": 88471, "category": "technology_software", "isanchordig": 1, "ischecked": 0, "isdelete": 0, "categoryclass": "technology", "via": null, "real_tags": ["adobe", "ppc", "photoshop", "\u8f6f\u4ef6"]}, {"url": "http://ipv6.google.cn", "title": "IPv4\u5730\u5740\u67af\u7aed \u8c37\u6b4c\u63a8\u51faIPv6\u4e2d\u6587\u641c\u7d22", "tags": "IPv4 IPv6 \u8c37\u6b4c google \u641c\u7d22 ", "name": "yinyin", "posttime": "2008-09-01 10:53:55", "ip": "117.88.34.32", "mark": 4, "note": "\u57fa\u4e8e IPv6 \u7684\u8c37\u6b4c\u82f1\u6587\u641c\u7d22\u5df2\u7ecf\u53ef\u4ee5\u5728 ipv6.google.com \u4f7f\u7528\uff0c\u73b0\u5728\u8c37\u6b4c\u4e2d\u6587\u641c\u7d22\u4e5f\u5df2\u542f\u7528\u8fd9\u4e00\u529f\u80fd(\u4f60\u7684\u7ec8\u7aef\u8fd8\u9700\u8981\u4e00\u4e2a IPv6 \u8fde\u63a5\u5c31\u80fd\u6d4f\u89c8)\u3002\r\n\u5b83\u76f4\u63a5\u63a5\u5165\u4e2d\u56fd\u4e0b\u4e00\u4ee3\u4e92\u8054\u7f51(CNGI)\uff0c\u56e0\u6b64\u53ef\u4ee5\u4e3a\u4e2d\u56fd\u548c\u5168\u4e16\u754c\u7684 IPv6 \u7528\u6237\u63d0\u4f9b\u4e2d\u6587\u641c\u7d22\u670d\u52a1\u3002\r\n\u5b83\u53ef\u4ee5\u8ba9\u4efb\u4f55\u4e00\u53f0\u8ba1\u7b97\u673a\u548c\u79fb\u52a8\u7ec8\u7aef\u90fd\u80fd\u5728\u7f51\u7edc\u4e4b\u4e2d\u81ea\u7531\u4ea4\u8c08(\u201c\u7aef\u5230\u7aef\u201d\u539f\u5219\u662f\u4e92\u8054\u7f51\u6700\u521d\u8bbe\u8ba1\u7684\u5173\u952e\u6027\u7684\u539f\u5219)\uff0cIPv6 \u5c06\u5e26\u6765\u4e92\u8054\u7f51\u7684\u6301\u7eed\u53d1\u5c55\uff0c\u8ba9\u4e92\u8054\u7f51\u5e94\u7528\u7684\u4e0d\u65ad\u521b\u65b0\u6210\u4e3a\u53ef\u80fd\u3002", "imagename": "dbde37718efc42fa917cf3868b66e9be.gif", "infoid": 88470, "category": "technology_google", "isanchordig": 1, "ischecked": 0, "isdelete": 0, "categoryclass": "technology", "via": null, "real_tags": ["ipv4", "ipv6", "\u8c37\u6b4c", "google", "\u641c\u7d22"]}]