[{"url": "http://www.downloadsquad.com/2006/12/01/seven-rules-for-web-2-0-startups/", "title": "Seven rules for Web 2.0 startups", "tags": "web2.0 ", "name": "daodao", "posttime": "2006-12-02 20:17:14", "ip": "59.53.195.132", "mark": 5, "note": "These days it seems like anyone with an idea and some time can crank out a Web 2.0 startup, be it a service, community, one-trick-pony or ambiguously named whichamadinger. It also seems like many of these startups could use some guidance to help them find their way. With goofy names, varying user experiences and questionable goals running amok, we figured it was time to lay down some ground rules. Check out our seven tips to help Web 2.0 startups be all they can be:\r\n\r\nHelp me make the move: New blogs and communities need easy tools to let their users integrate some sort of blurb about their new hangout on their other sites and communities. For example: I\u2019ve been playing with Vox for a few weeks now, and just recently they introduced a badge tool that puts together all the HTML users woul", "imagename": "", "infoid": 9937, "category": "technology_web2", "isanchordig": 1, "ischecked": 1, "isdelete": 0, "categoryclass": "technology", "via": null, "real_tags": ["web2.0"]}, {"url": "http://www.blogcn.com/u2/94/98/fight4what/blog/47699203.html", "title": "\u7ef4\u57fa\u767e\u79d1LOGO\u4e0a\u7684\u90a3\u4e2a\u4e2d\u6587\u5b57\u662f\u201c\u8893\u201d\uff0c\u4e0d\u662f\u201c\u7956\u201d", "tags": "\u7ef4\u57fa\u767e\u79d1 logo \u8893 ", "name": "fight4what", "posttime": "2006-12-02 19:16:13", "ip": "218.19.67.75", "mark": 14, "note": "\u7ef4\u57fa\u767e\u79d1LOGO\u4e0a\u7684\u4e2d\u6587\u5b57\u201c\u8893\u201d\uff0c\u5e38\u5e38\u88ab\u8bef\u4ee5\u4e3a\u662f\u7956\u5148\u7684\u201c\u7956\u201d\uff0c\u5176\u5b9e\u201c\u8893\u201d\u5b57\u662f&quot;\u8863&quot;\u5b57\u65c1\uff0c\u5e76\u975e&quot;\u793a&quot;\u5b57\u65c1\u3002\n\n    \u201c\u8893\u201d\u5b57\u6709\u4e24\u79cd\u8bfb\u97f3\uff1a1\u3001j&#249;  \u4e8b\u597d\u3001\u8272\u767d\u4e4b\u7f8e       2\u3001ji\u0113 \uff08\uff5e\u5389\u3015\u53e4\u53bf\u540d", "imagename": "bb9af4b9-041e-4f30-9d95-19896b0a4edc.jpg", "infoid": 9933, "category": "technology_internet", "isanchordig": 1, "ischecked": 1, "isdelete": 0, "categoryclass": "technology", "via": null, "real_tags": ["\u7ef4\u57fa\u767e\u79d1", "logo"]}, {"url": "http://www.kuju.cn/post/456.html", "title": "100\u4e07\u7f8e\u5143\uff0c\u60f3\u8981\u5417\uff1f", "tags": "Million Dollar ", "name": "kuju", "posttime": "2006-12-02 17:08:46", "ip": "59.56.177.108", "mark": 5, "note": "\u8fd8\u8bb0\u5f97\u767e\u4e07\u7f8e\u5143\u4e3b\u9875\uff08The Million Dollar Homepage\uff09\u5417\uff1f,Alex Tew\u4ee5\u6bcf\u50cf\u7d201\u7f8e\u5143\u7684\u4ef7\u683c\u51fa\u552e\uff0c\u7ed3\u679c\u8db3\u8db3\u8d5a\u4e86100\u4e07\u7f8e\u5143\u3002\u7531\u4e8e\u5176\u5929\u624d\u7684\u60f3\u6cd5\uff0c\u88ab\u5404\u5927\u5a92\u4f53\u6240\u62a5\u9053\u3002\u6700\u8fd1Tew\u6709\u4e86\u4e00\u4e2a\u65b0\u7684\u60f3\u6cd5\uff0c\u4ed6\u6b63\u5728\u5efa\u7acb\u4e00\u4e2a\u65b0\u7684\u7f51\u7ad9Pixelotto\u3002\u8fd9\u4e00\u6b21\uff0c\u4ed6\u8ba1\u5212\u4ee5\u6bcf\u50cf\u7d202\u7f8e\u5143\u7684\u4ef7\u683c\u51fa\u552e\uff0c\u5982\u679c\u5168\u90e8\u51fa\u552e\u5c06\u4f1a\u6709200\u4e07\u7f8e\u5143\u7684\u6536\u5165\u3002\u5176\u4e2d100\u4e07\u5c06\u4f5c\u4e3a\u5956\u54c1\uff0c\u8bbf\u95ee\u8005\u5982\u679c\u70b9\u5230\u4e86\u67d0\u4e2a\u9884\u5148\u786e\u5b9a\u7684\u5e7f\u544a\u50cf\u7d20\u7684\u8bdd\u5c06\u5f97\u5230\u8fd9100\u4e07\u3002", "imagename": "", "infoid": 9928, "category": "technology_internet", "isanchordig": 1, "ischecked": 1, "isdelete": 0, "categoryclass": "technology", "via": null, "real_tags": ["million", "dollar"]}, {"url": "http://skeletonproject.com/2006/11/28/10-movies-the-us-government-would-prefer-people-not-watch/", "title": "10 films the US Government would rather you not see", "tags": "movie ", "name": "watsonxu", "posttime": "2006-12-02 16:29:58", "ip": "58.196.157.71", "mark": 10, "note": "10\u90e8\u7f8e\u56fd\u653f\u5e9c\u4e0d\u5e0c\u671b\u516c\u4f17\u89c2\u770b\u7684\u7535\u5f71,\u5475\u5475\uff0c\u60f3\u4e0d\u5230\u7f8e\u56fd\u653f\u5e9c\u4e5f\u6709\u62c5\u5fc3\u7684", "imagename": "", "infoid": 9927, "category": "technology_other", "isanchordig": 1, "ischecked": 1, "isdelete": 0, "categoryclass": "technology", "via": null, "real_tags": ["movie"]}, {"url": "http://dumblittleman.blogspot.com/2006/11/250-free-office-templates-and-documents.html", "title": "250 Free Office Templates and Documents", "tags": "web office ", "name": "watsonxu", "posttime": "2006-12-02 15:53:14", "ip": "58.196.157.71", "mark": 13, "note": "250\u4e2a\u5b9e\u7528\u7f8e\u89c2\u7684office\u6a21\u677f,\u975e\u5e38\u7684\u4e0d\u9519\uff0cshare", "imagename": "08219bfb-74b0-4491-81b4-5931e306da10.png", "infoid": 9926, "category": "technology_web2", "isanchordig": 1, "ischecked": 1, "isdelete": 0, "categoryclass": "technology", "via": null, "real_tags": ["web", "office"]}, {"url": null, "title": "\u4e00\u4e9b\u9177\u7ad9\u8fde\u63a5website awards", "tags": "\u9177\u7ad9 links website awards ", "name": "acridnina", "posttime": "2006-12-02 15:38:11", "ip": "124.248.18.24", "mark": 21, "note": "\u524d\u4eba\u5df2\u7ecf\u4ecb\u7ecd\u4e86\u597d\u51e0\u4e2a\u7ad9\u70b9,\u4eca\u513f\u518d\u62ff\u51fa\u6765\u667e\u667e,\u820d\u4e0d\u5f97\u57cb\u6ca1\u4e86\u597d\u6587.\u5176\u672c\u8eab\u5c31\u662f\u9177\u7ad9,\u91cc\u9762\u6536\u96c6\u7684\u4e5f\u5c3d\u662f\u9177\u7ad9.", "imagename": null, "infoid": 9925, "category": "technology_internet", "isanchordig": 1, "ischecked": 1, "isdelete": 0, "categoryclass": "technology", "via": null, "real_tags": ["\u9177\u7ad9", "links", "website", "awards"]}, {"url": "http://www.maming.org/blog/article.asp?id=11", "title": "Labpixies:\u7f51\u7edc\u4e0a\u6700\u9177\u7684widgets", "tags": "widgets ", "name": "maming", "posttime": "2006-12-02 13:53:01", "ip": "218.69.100.58", "mark": 5, "note": "\u4e3b\u9875\u4e0a\u63d0\u4f9b\u4e86\u5f88\u591awidgets,\u4f60\u53ef\u4ee5\u76f4\u63a5\u628a\u8fd9\u4e9bwidgets\u52a0\u5165\u5230\u4f60\u7684Google\u4e3b\u9875\uff0cWindows live, Netvibes, PageFlakes\u7b49\u4e2a\u6027\u5316\u4e3b\u9875\uff0c\u4f60\u4e5f\u53ef\u4ee5\u6309\u7167\u6e38\u620f\uff0c\u5a31\u4e50\uff0c\u5de5\u5177\u4e0d\u540c\u7684\u5206\u7c7b\u6765\u6d4f\u89c8\u9009\u62e9\u4e0d\u540c\u7684widgets,\u5f97\u5230\u4ee3\u7801\u76f4\u63a5\u52a0\u5165\u5230\u4f60\u7684\u7f51\u7ad9\u6216\u8005blog\u4e2d", "imagename": "ce07c548-a7e4-4ef5-81f6-1cfc6dc6d46f.jpg", "infoid": 9920, "category": "technology_web2", "isanchordig": 1, "ischecked": 1, "isdelete": 0, "categoryclass": "technology", "via": null, "real_tags": ["widgets"]}, {"url": "http://www.10166.com.cn/", "title": "\u8054\u901aIM\u201c\u8d85\u4fe1\u201d\u6b63\u5f0f\u4e0a\u7ebf", "tags": "\u8054\u901a IM \u8d85\u4fe1 ", "name": "yahooor", "posttime": "2006-12-02 12:36:03", "ip": "211.137.144.42", "mark": 6, "note": "\u8d85\u4fe1\u662f\u4e2d\u56fd\u8054\u901a\u7684\u7efc\u5408\u5373\u65f6\u901a\u4fe1\u670d\u52a1\uff0c\u8d85\u4fe1\u7684\u7528\u6237\u53ef\u4ee5\u901a\u8fc7\u624b\u673a\u5ba2\u6237\u7aef\uff08BREW\u3001Unija\uff09\u3001PC\u5ba2\u6237\u7aef\u3001\u77ed\u4fe1\u5ba2\u6237\u7aef\u3001WAP\u5ba2\u6237\u7aef\u3001IVR\u5ba2\u6237\u7aef\u591a\u79cd\u624b\u6bb5\u968f\u65f6\u4f7f\u7528\u8d85\u4fe1\u670d\u52a1\uff0c\u8fdb\u884c\u624b\u673a\u5230\u624b\u673a\uff0c\u624b\u673a\u5230PC\u7684\u6587\u5b57\u3001\u8868\u60c5\u3001\u56fe\u7247\u3001\u8bed\u97f3\u7b49\u4fe1\u606f\u7684\u5373\u65f6\u4e92\u901a\u3002 \r\n         \u8d85\u4fe1\u65e8\u5728\u6253\u9020\u6700\u65b9\u4fbf\u6700\u65f6\u5c1a\u7684\u624b\u673a\u4ea4\u53cb\u4e2d\u5fc3\uff0c\u8ba9\u4f60\u968f\u65f6\u968f\u5730\u548c\u597d\u53cb\u4fdd\u6301\u4eb2\u5bc6\u8054\u7cfb\u3002\u8fd8\u5728\u7b49\u4ec0\u4e48\uff1f\u8d76\u7d27\u52a0\u5165\u5427\uff01\u65e0\u6570\u7f8e\u5973\u5e05\u54e5\u7b49\u4f60\u503e\u8bc9...", "imagename": "edb0707c-00f4-4995-a42b-258382972d46.gif", "infoid": 9918, "category": "technology_software", "isanchordig": 1, "ischecked": 1, "isdelete": 0, "categoryclass": "technology", "via": null, "real_tags": ["\u8054\u901a", "im", "\u8d85\u4fe1"]}, {"url": "http://msnsa.net/tools/city-day-night.swf", "title": "\u8f7b\u677e\u4e00\u4e0b-\u5929\u9ed1\u4e86\u5929\u4eae\u4e86\uff0c\u4e00\u4e2a\u6709\u8da3\u7684flash", "tags": "\u8da3\u56fe ", "name": "dutmcse", "posttime": "2006-12-02 08:50:53", "ip": "72.38.220.11", "mark": 6, "note": "\u4e0b\u9762\u8fd9\u4e2a\u56fe\u5f88\u6709\u610f\u601d\uff0c\u8bd5\u8bd5\u7528\u4f60\u7684\u9f20\u6807\u4ece\u56fe\u7684\u53f3\u4fa7\u6ed1\u5230\u5de6\u4fa7\uff0c\u770b\u770b\u662f\u4e0d\u662f\u5929\u4eae\u4e86^_^\uff0c \u4ece\u5de6\u8fb9\u5230\u53f3\u8fb9\uff0c\u662f\u4e0d\u662f\u5929\u9ed1\u4e86\uff1f\uff01\u5f88\u6709\u8da3\uff0c\u548c\u5927\u5bb6\u5206\u4eab\u4e00\u4e0b\uff1a", "imagename": "c41041aa-2748-45f9-a52b-d32171dd6194.jpg", "infoid": 9915, "category": "technology_internet", "isanchordig": 1, "ischecked": 1, "isdelete": 0, "categoryclass": "technology", "via": null, "real_tags": ["\u8da3\u56fe"]}, {"url": "http://www.lwk.dk/MugMouse/Mugmluse_content.html", "title": "\u5496\u5561\u676f?\u9f20\u6807?", "tags": "\u786c\u4ef6 \u9f20\u6807 ", "name": "acridnina", "posttime": "2006-12-01 22:04:48", "ip": "124.248.21.100", "mark": 8, "note": "MugMouse\u4e00\u7269\u4e24\u7528,\u771f\u662f\u65b9\u4fbf\u554a,\u53ea\u8981\u4e0d\u79fb\u52a8\u7684\u592a\u5feb\u8f7b\u8f7b\u70b9\u51fb,\u4f46\u662f\u600e\u4e48\u4f7f\u7528\u53f3\u952e\u529f\u80fd\u5462", "imagename": "e8793a37-85a2-4889-94cd-a5b225edf6b5.jpg", "infoid": 9905, "category": "technology_hardware", "isanchordig": 1, "ischecked": 1, "isdelete": 0, "categoryclass": "technology", "via": null, "real_tags": ["\u786c\u4ef6", "\u9f20\u6807"]}, {"url": "http://www.therawfeed.com/2006/10/giant-bubble-helmet-gives-360-degree.html", "title": "360\u5ea6\u770b\u7535\u89c6", "tags": "360\u5ea6 \u7535\u89c6 ", "name": "acridnina", "posttime": "2006-12-01 21:43:22", "ip": "124.248.21.100", "mark": 8, "note": "\u4e1c\u829d\u5c06\u63a8\u51fa\u53ef\u4ee5360\u5ea6\u770b\u7535\u89c6\u73a9\u6e38\u620f\u7684GLANT BUBBLE HELMET,\u8fd9\u4e2a\u602a\u7269\u91cd\u8fbe5\u65a4,\u6234\u5728\u5934\u4e0a\u4e0d\u77e5\u9053\u8116\u5b50\u5403\u4e0d\u5403\u5f97\u6d88,\u770b\u89c6\u9891http://www.tv-tokyo.co.jp/wbs/2006/10/27/movie/tt.ram", "imagename": "96db039d-28c1-47e9-b34c-c5e04105222f.jpg", "infoid": 9904, "category": "technology_hardware", "isanchordig": 1, "ischecked": 1, "isdelete": 0, "categoryclass": "technology", "via": null, "real_tags": ["360\u5ea6", "\u7535\u89c6"]}, {"url": "http://gz520.net/zuozi/?p=169", "title": "Blog\u5de5\u5177\u603b\u7ed3", "tags": "web blog ", "name": "watsonxu", "posttime": "2006-12-01 21:13:48", "ip": "58.196.157.71", "mark": 13, "note": "\u603b\u7ed3\u5f88\u5168\u7684blog\u5de5\u5177\u5927\u5168\uff0c\u5f88\u4e0d\u9519\uff0c\u548c\u5927\u5bb6\u5206\u4eab", "imagename": "", "infoid": 9903, "category": "technology_web2", "isanchordig": 1, "ischecked": 1, "isdelete": 0, "categoryclass": "technology", "via": null, "real_tags": ["web", "blog"]}, {"url": "http://www.billgatesforpresident.net/", "title": "Bill Gates for President!", "tags": "microsoft \u5fae\u8f6f USA \u7f8e\u56fd \u603b\u7edf ", "name": "shizhao", "posttime": "2006-12-01 16:35:02", "ip": "210.72.12.72", "mark": 9, "note": "\u8ba9\u6bd4\u5c14&#183;\u76d6\u8328\u5f53\u603b\u7edf", "imagename": "", "infoid": 9891, "category": "technology_other", "isanchordig": 1, "ischecked": 1, "isdelete": 0, "categoryclass": "technology", "via": null, "real_tags": ["microsoft", "\u5fae\u8f6f", "usa", "\u7f8e\u56fd", "\u603b\u7edf"]}, {"url": "http://rionkdr.blogspot.com/2006/12/blogger-beta.html", "title": "Blogger Beta\u540e\u53f0\u7ec8\u4e8e\u5b8c\u5168\u4e2d\u6587\u5316\uff01\uff01\uff01", "tags": "blogger ", "name": "rionkdr", "posttime": "2006-12-01 15:08:13", "ip": "218.19.49.119", "mark": 9, "note": "\u540e\u53f0\u5b8c\u5168\u6c49\u5316\u4e86\uff01\uff01\u8bf7\u70b9\u51fb\u56fe\u7247\uff0c\u4e8e\u662f\uff0c\u8fd8\u6709\u4e0d\u7528Blogger\u7684\u7406\u7531\u5417\uff1f", "imagename": "", "infoid": 9888, "category": "technology_google", "isanchordig": 1, "ischecked": 1, "isdelete": 0, "categoryclass": "technology", "via": null, "real_tags": ["blogger"]}, {"url": "http://www.williamlong.info/archives/708.html", "title": "\u767e\u5ea6\u641c\u85cf\u7684\u529f\u80fd\u7f3a\u9677 - \u6708\u5149\u535a\u5ba2", "tags": "\u767e\u5ea6 ", "name": "elfox", "posttime": "2006-12-01 14:57:49", "ip": "211.158.51.238", "mark": 5, "note": "\u767e\u5ea6\u7684\u7f51\u7edc\u6536\u85cf\u5939\u670d\u52a1\u201c\u767e\u5ea6\u641c\u85cf\u201d\u5df2\u7ecf\u53d1\u5e03\u4e86\uff0c\u6211\u4e5f\u7b2c\u4e00\u65f6\u95f4\u8bd5\u7528\u4e86\u4e00\u4e0b\uff0c\u611f\u89c9\u767e\u5ea6\u641c\u85cf\u6709\u4e0d\u5c11\u529f\u80fd\u4e0a\u7684\u7f3a\u9677\u4ee4\u4eba\u611f\u5230\u5f88\u9057\u61be\uff0c\u793e\u4f1a\u5316\u529f\u80fd\u5f88\u5f31\uff0c\u901f\u5ea6\u4e5f\u4e0d\u662f\u5f88\u5feb\uff0c\u4e0d\u8fc7\u641c\u7d22\u529f\u80fd\u7684\u786e\u662f\u505a\u7684\u4e0d\u9519\u3002", "imagename": "60297618-6261-4cfe-ae21-f104dbab3718.jpg", "infoid": 9886, "category": "technology_internet", "isanchordig": 1, "ischecked": 1, "isdelete": 0, "categoryclass": "technology", "via": null, "real_tags": ["\u767e\u5ea6"]}]